sightlines/cell.py
sightlines/cell_functions/buildkite.py
sightlines/cell_functions/pagerduty.py
sightlines/cell_functions/rainbow.py
sightlines/cell_runner.py
sightlines/grid.py
sightlines/thread_safety_test.py
sightlines-0.3.0.dist-info/entry_points.txt
sightlines-0.3.0.dist-info/LICENSE.txt
sightlines-0.3.0.dist-info/WHEEL
sightlines-0.3.0.dist-info/METADATA
sightlines-0.3.0.dist-info/RECORD
