Metadata-Version: 2.1
Name: sightlines
Version: 0.3.0
Summary: 
Author: Toby McLaughlin
Author-email: toby@jarpy.net
Requires-Python: >=3.10,<4.0
Classifier: Programming Language :: Python :: 3
Classifier: Programming Language :: Python :: 3.10
Classifier: Programming Language :: Python :: 3.11
Requires-Dist: apscheduler (>=3.9.1.post1,<4.0.0)
Requires-Dist: launchpad-py (>=0.9.1,<0.10.0)
Requires-Dist: pdpyras (>=4.5.2,<5.0.0)
Requires-Dist: pygame (<2.1.3)
Requires-Dist: python-dateutil (>=2.8.2,<3.0.0)
Requires-Dist: requests (>=2.28.1,<3.0.0)
